bert_score_cli/__init__.py
bert_score_cli/score.py
bert_score_cli/visualize.py
bert_score_flex_plot_example/__init__.py
bert_score_flex_plot_example/score.py
bert_score_flex_plot_example/scorer.py
bert_score_flex_plot_example/utils.py
bert_score_flex_plot_example-0.3.16.dist-info/LICENSE
bert_score_flex_plot_example-0.3.16.dist-info/METADATA
bert_score_flex_plot_example-0.3.16.dist-info/WHEEL
bert_score_flex_plot_example-0.3.16.dist-info/entry_points.txt
bert_score_flex_plot_example-0.3.16.dist-info/top_level.txt
bert_score_flex_plot_example-0.3.16.dist-info/RECORD
