Metadata-Version: 2.1
Name: bert_score_flex_plot_example
Version: 0.3.16
Summary: An unofficial fork of PyTorch implementation of BERT score
Home-page: https://github.com/Amannor/bert_score/tree/flex_plot_example
Author: Fork author: Alon Mannor. Origianl authors: Tianyi Zhang*, Varsha Kishore*, Felix Wu*, Kilian Q. Weinberger, and Yoav Artzi
Author-email: alon.mannor@gmail.com (fork author),  tzhang@asapp.com (original author)
License: MIT
Keywords: BERT NLP deep learning google metric
Classifier: Intended Audience :: Science/Research
Classifier: License :: OSI Approved :: MIT License
Classifier: Programming Language :: Python :: 3
Classifier: Topic :: Scientific/Engineering :: Artificial Intelligence
Requires-Python: >=3.6
License-File: LICENSE
Requires-Dist: torch >=1.0.0
Requires-Dist: pandas >=1.0.1
Requires-Dist: transformers >=3.0.0
Requires-Dist: numpy
Requires-Dist: requests
Requires-Dist: tqdm >=4.31.1
Requires-Dist: matplotlib
Requires-Dist: packaging >=20.9
